Workbook

Sheet Dashboard
A1: Dashboard
A2: Your whole picture — pulled live from the other tabs.
A4: THE NUMBERS THAT MATTER
A6: Net worth (this month) | D6: Total owed
A7: ='Net Worth'!B24 | D7: =Debts!B10
A8: climbs as debt drops | D8: Visa first
A10: Monthly leftover (from pay) | D10: Consumer debt (the beatable part)
A11: =Budget!B26 | D11: =Debts!B11
A12: after rent, bills, groceries | D12: Visa+Dad+PC+student
A14: Vapes & convenience — latest | D14: Credit score
A15: =Vapes!B6 | D15: 715
A16: target under $300 → see Vapes tab | D16: Good — up from 630
A18: THE PLAN, IN ORDER
A19: 1. Cut vapes/convenience toward $300 → frees ~$1,000/mo
A20: 2. Move Visa to CIBC 0%, then crush it
A21: 3. Build emergency fund: 1 month → 3 months (~$10k)
A22: 4. Lock protection: will, life & disability check
A23: 5. RESP for your kid (free 20%), then FHSA + investing

Sheet README
A1: Steven's Money Workbook
A2: A companion to your Life Planner — the engine room where the numbers live.
B4: HOW TO USE THIS
B5: Tabs across the bottom. Type into the YELLOW cells; the rest calculate themselves.
B6: Blue text = a number you enter. Black = a formula. Green = pulled from another tab.
B8: THE TABS | C8: What it does
B9: Dashboard | C9: Your whole picture at a glance — updates from every other tab.
B10: Budget | C10: Monthly plan vs. actual by category. 'Actual' fills in from Transactions.
B11: Transactions | C11: Log spending here (or paste from your statement). Feeds the Budget.
B12: Bills | C12: Every recurring bill, amount, due day, auto or manual.
B13: Debts | C13: Payoff tracker — avalanche order (highest rate first).
B14: Net Worth | C14: Assets minus debts, with a column per month so you watch it climb.
B15: Savings & Sinking Funds | C15: Emergency fund + money set aside monthly for irregular costs.
B16: Vapes & Convenience | C16: Your #1 target — track it falling month over month.
B18: THINGS WE ADDED THAT MOST PEOPLE MISS
B19: • Net worth tracked over TIME (not just one number) — proof you're climbing.
B20: • Sinking funds — saving monthly for irregular costs (tires, gifts, trips) so they never ambush you.
B21: • Two income streams kept separate — your pay vs. the work reimbursement.
B22: • A savings-rate % so you can see what portion of your pay you actually keep.

Sheet Budget
A1: Monthly Budget
A2: 'Planned' = your TARGET. 'Actual' = real July spending, summed from the Transactions tab. Rent, hydro & student loan are paid outside your day-to-day account, so they show their set amount. Car loan & gas aren't here — your work reimbursement covers those.
A4: Category | B4: Planned | C4: Actual | D4: Difference | E4: Notes
A5: INCOME
A6: Take-home pay (2 cheques) | B6: 3644 | E6: Net pay $1,822 × 2. More in 3-payday months + commission.
A7: Hannah's contribution | B7: 1968 | E7: Now: her real transfers avg ~$1,968/mo (EI + child benefits). ⚠ DROPS after Oct when EI ends — see the 'After October' block below.
A8: Instacart / side income | B8: 0 | E8: Your growth lever — fill in as it comes.
A9: Total income | B9: =SUM(B6:B8)
A11: EXPENSES
A12: Rent | B12: 1900 | C12: =Bills!B5 | D12: =B12-C12 | E12: 1st (paid ~26th prior month by e-transfer)
A13: Insurance (home+auto) | B13: 402.88 | C13: =SUMIF(Transactions!$C:$C,A13,Transactions!$D:$D) | D13: =B13-C13 | E13: Belair, 7th — requote the auto side
A14: Phone (Telus, both lines) | B14: 90 | C14: =SUMIF(Transactions!$C:$C,A14,Transactions!$D:$D) | D14: =B14-C14 | E14: $35 you + $55 Hannah
A15: Internet (Rogers) | B15: 90 | C15: =SUMIF(Transactions!$C:$C,A15,Transactions!$D:$D) | D15: =B15-C15 | E15: TARGET — real bill is $143.99 (1.5 Gbps + $10 gateway). Downgrade the plan to hit this.
A16: Hydro (Grandbridge) | B16: 115.99 | C16: =Bills!B6 | D16: =B16-C16 | E16: actual — $115.99 due Sep 2
A17: Student loan | B17: 54 | C17: =Bills!B11*26/12 | D17: =B17-C17 | E17: $25 biweekly
A18: Groceries | B18: 800 | C18: =SUMIF(Transactions!$C:$C,A18,Transactions!$D:$D) | D18: =B18-C18 | E18: TARGET (July was $975)
A19: Vapes & convenience | B19: 300 | C19: =SUMIF(Transactions!$C:$C,A19,Transactions!$D:$D) | D19: =B19-C19 | E19: TARGET (July was $1,205) — see Vapes tab
A20: Takeout (personal) | B20: 300 | C20: =SUMIF(Transactions!$C:$C,A20,Transactions!$D:$D) | D20: =B20-C20 | E20: TARGET (July was $826)
A21: Subscriptions | B21: 150 | C21: =SUMIF(Transactions!$C:$C,A21,Transactions!$D:$D) | D21: =B21-C21 | E21: TARGET — trim the overlap
A22: Household / other | B22: 150 | C22: =SUMIF(Transactions!$C:$C,A22,Transactions!$D:$D) | D22: =B22-C22 | E22: TARGET
A23: Health / pharmacy | B23: 200 | C23: =SUMIF(Transactions!$C:$C,A23,Transactions!$D:$D) | D23: =B23-C23 | E23: TARGET
A24: Total expenses | B24: =SUM(B12:B23) | C24: =SUM(C12:C23)
A26: LEFT OVER (income − expenses) | B26: =B9-B24
A27: Savings rate (leftover ÷ take-home pay) | B27: =IFERROR(B26/B6,0)
A29: LIFE CHANGE COMING — Hannah home, EI ends October
A30: You both want Hannah home for the baby + homeschool. That's a real, doable choice — here's the honest math for after October:
A31: Steven's take-home pay | B31: 3644 | E31: your pay
A32: Child benefits (CCB, est.) | B32: 700 | E32: continues — and often RISES when income drops. Confirm your amount.
A33: Instacart / side income | B33: 0 | E33: YOUR lever — this is what closes the gap
A34: Income after Oct | B34: =SUM(B31:B33)
A35: Minus target expenses | B35: =-B24
A36: Left over after Oct | B36: =B34-B24
A37: If negative: a bit of Instacart + your commission months close it. The vape cut is what makes it work at all.

Sheet Transactions
A1: Transactions — July 2026 (your real spending)
A2: Every purchase from your July statement, sorted by date. The Budget's 'Actual' column sums these by Category. Internal transfers, e-transfers, card payments & the car loan are left out on purpose — this is spending, not money moving between accounts.
A4: Date | B4: Description | C4: Category | D4: Amount
A5: 2026-07-02 | B5: BULK BARN #639 | C5: Groceries | D5: 89.12
A6: 2026-07-02 | B6: BURGER KING #29 | C6: Takeout (personal) | D6: 38.37
A7: 2026-07-02 | B7: CAMBRIDGE GB 62 | C7: Vapes & convenience | D7: 66.09
A8: 2026-07-02 | B8: DOLLARAMA #1168 | C8: Household / other | D8: 71.76
A9: 2026-07-02 | B9: GALT MINI MART | C9: Vapes & convenience | D9: 8.45
A10: 2026-07-02 | B10: GALT MINI MART | C10: Vapes & convenience | D10: 51.97
A11: 2026-07-02 | B11: PLAYSTATIO | C11: Subscriptions | D11: 23.72
A12: 2026-07-02 | B12: ROSS LINDSAY' | C12: Groceries | D12: 52.86
A13: 2026-07-02 | B13: SHOPPERS DRUG M | C13: Health / pharmacy | D13: 24.18
A14: 2026-07-02 | B14: TOKYO SMOKE 420 | C14: Vapes & convenience | D14: 23.73
A15: 2026-07-02 | B15: ZEHRS S CAMBRID | C15: Groceries | D15: 82.18
A16: 2026-07-03 | B16: FOOD BASICS 63 | C16: Groceries | D16: 348.83
... A146: 2026-07-31 | B146: TD monthly account fee | C146: Household / other | D146: 17.95
B147: July total spending → | D147: =SUM(D5:D146)
A149: Add new months below — pick a Category from the dropdown so it flows into the Budget:

Sheet Bills
A1: Bills
A2: Every recurring bill. Yellow = edit.
A4: Bill | B4: Amount | C4: Due day | D4: Frequency | E4: Pay type
A5: Rent | B5: 1900 | C5: 1st | D5: Monthly | E5: Manual e-transfer
A6: Hydro (Grandbridge) | B6: 115.99 | C6: 2nd | D6: Monthly | E6: Manual — $115.99 due Sep 2 (acct …0324-04)
A7: Insurance (home+auto) | B7: 402.88 | C7: 7th | D7: Monthly | E7: Auto-debit
A8: Phone (Telus) | B8: 90 | C8: ~10th | D8: Monthly | E8: Manual → set autopay
A9: Internet (Rogers) | B9: 143.99 | C9: 28th | D9: Monthly | E9: Autopay — ⚠ 1.5 Gbps plan is overkill. Downgrade to save ~$50-60/mo
A10: Car loan (VW) | B10: 302.9 | C10: Fri | D10: Biweekly | E10: Auto
A11: Student loan (NSLSC) | B11: 25 | C11: — | D11: Biweekly | E11: Auto
A12: TD Visa (min) | B12: 65.55 | C12: 17th | D12: Monthly | E12: Manual → moving to CIBC 0%
A13: Total monthly bills* | B13: =B5+B6+B7+B8+B9+(B10+B11)*26/12
A14: *biweekly items converted to a monthly average

Sheet Debts
A1: Debt Payoff — avalanche order
A2: Highest interest first. Update the balance as you pay. Yellow = edit.
A4: Debt | B4: Balance | C4: Rate | D4: Min / mo | E4: % paid off | F4: Note | G4: (original)
A5: TD Visa | B5: 1359.07 | C5: 0.27 | D5: 65.55 | E5: =IFERROR(1-B5/G5,0) | F5: #1 — move to CIBC 0%, then crush it. Paid $80 + $65.55; down from $1,455 | G5: 1455
A6: Dad (personal) | B6: 0 | C6: 0 | D6: 0 | E6: =IFERROR(1-B6/G6,0) | F6: WAIVED by Dad ✓ — stays gone as long as you hold $500+ in savings from Sept 1 & keep growing it | G6: 800
A7: Brother's PC | B7: 400 | C7: 0 | D7: 0 | E7: =IFERROR(1-B7/G7,0) | F7: 0% family | G7: 950
A8: Student loan | B8: 614 | C8: 0.03 | D8: 25 | E8: =IFERROR(1-B8/G8,0) | F8: nearly gone | G8: 1000
A9: Car loan (VW) | B9: 38886 | C9: 0.0529 | D9: 302.9 | E9: =IFERROR(1-B9/G9,0) | F9: paid by work reimbursement — leave it | G9: 42000
A10: Total owed | B10: =SUM(B5:B9)
A11: Consumer debt (excl. car) | B11: =SUM(B5:B8)

Sheet Net Worth
A1: Household Net Worth (Steven + Hannah)
A2: Update a column each month. Watching it climb is the real scoreboard. Yellow = edit.
A4: Item | B4: Jul 2026 | C4: Aug 2026 | D4: Sep 2026 | E4: Oct 2026 | F4: Notes
A5: ASSETS
A6: Steven — TD chequing | B6: 107.26 | F6: real-time, low — transient
A7: Steven — CIBC chequing (Sept vault) | B7: 1615 | F7: the vault — Sept bills, held untouched
A8: Steven — CIBC savings (★$500 goal ✓) | B8: 500.01 | F8: $500 goal HIT Aug 18 — keeps Dad's $800 waiver while held
A9: Hannah — RBC chequing | B9: 113 | F9: she forwards ~$1,968/mo to the family; runs near $0
A10: Hannah — RPP (work pension) | B10: 4369.56 | F10: +15.6% YTD. Small locked pension — transfer to RRSP/LIRA, don't cash if you can help it
A11: Hannah — DPSP (work) | B11: 3578.67 | F11: +17.7% YTD. Transfer to an RRSP TAX-FREE (Form T2151) — cashing it is taxed + loses the growth
A12: TFSA / RRSP / investments | B12: 0 | F12: none yet — the future
A13: Car (market value) | B13: 28000 | F13: estimate — check a trade-in value
A14: Total assets | B14: =SUM(B6:B13) | C14: =SUM(C6:C13) | D14: =SUM(D6:D13) | E14: =SUM(E6:E13)
A16: LIABILITIES (what you owe)
A17: TD Visa | B17: 1359.07
A18: Dad (waived ✓) | B18: 0
A19: Brother's PC | B19: 400
A20: Student loan | B20: 614
A21: Car loan | B21: 38886
A22: Total owed | B22: =SUM(B17:B21) | C22: =SUM(C17:C21) | D22: =SUM(D17:D21) | E22: =SUM(E17:E21)
A24: NET WORTH | B24: =B14-B22 | C24: =C14-C22 | D24: =D14-D22 | E24: =E14-E22
A25: Negative for now (the car loan). The number climbing each month is what matters.
A26: All debts above are Steven's — Hannah carries none (she uses debit, no credit debt). Good for the household.
A27: Hannah's RPP+DPSP = $7,948 of real retirement savings, growing ~16%/yr. Adding them lifts household net worth a lot.
A28: EI ENDS OCTOBER 2026 — plan is Hannah stays home (baby + homeschool). Her contribution then drops to mostly child benefits.

Sheet Savings
A1: Savings & Sinking Funds
A2: Sinking funds = save a little monthly for big irregular costs so they never ambush you. Yellow = edit.
A4: Goal / fund | B4: Target | C4: Saved so far | D4: Monthly set-aside | E4: Notes
A5: EMERGENCY FUND (the ladder)
A6: ★ $500 goal — HIT Aug 18 ✓ (keeps Dad's waiver) | B6: 500 | C6: 500 | D6: 500 | E6: DONE early! Dad waives the $800 as long as you HOLD this $500+. Don't spend it down.
A7: 1 month of essentials | B7: 4400 | C7: 0 | D7: 100 | E7: first real safety net
A8: 3 months (full e-fund) | B8: 10000 | C8: 0 | D8: 100 | E8: the target — automate it
A10: SINKING FUNDS (irregular costs)
A11: Car maintenance / tires | B11: 1200 | C11: 0 | D11: 100 | E11: ~$1,200/yr ÷ 12
A12: Gifts (birthdays, holidays) | B12: 600 | C12: 0 | D12: 50 | E12: so December isn't a shock
A13: Great Wolf Lodge trip | B13: 800 | C13: 0 | D13: 70 | E13: the family trip — pick a date
A14: Annual fees / renewals | B14: 300 | C14: 0 | D14: 25 | E14: any once-a-year charges
A15: Buffer / misc | B15: 0 | C15: 0 | D15: 0 | E15: add your own
A16: Total set aside each month | D16: =SUM(D6:D8)+SUM(D11:D15)

Sheet Vapes
A1: Vapes & Convenience — the #1 target
A2: Log the monthly total from each statement and watch it fall. Target: under $300/mo.
A4: Month | B4: Total spent | C4: Target | D4: Under target? | E4: Notes
A5: Jul 2026 | B5: 1163 | C5: 300 | D5: =IF(B5<=C5,"YES ✓","over by "&TEXT(B5-C5,"$#,##0"))
A6: Aug 2026 (partial) | B6: 195 | C6: 300 | D6: =IF(B6<=C6,"YES ✓","over by "&TEXT(B6-C6,"$#,##0"))
A7: Sep 2026 | C7: 300 | D7: =IF(B7="","",IF(B7<=C7,"YES ✓","over by "&TEXT(B7-C7,"$#,##0")))
A8: Oct 2026 | C8: 300 | D8: =IF(B8="","",IF(B8<=C8,"YES ✓","over by "&TEXT(B8-C8,"$#,##0")))
A9: Nov 2026 | C9: 300 | D9: =IF(B9="","",IF(B9<=C9,"YES ✓","over by "&TEXT(B9-C9,"$#,##0")))
A10: Dec 2026 | C10: 300 | D10: =IF(B10="","",IF(B10<=C10,"YES ✓","over by "&TEXT(B10-C10,"$#,##0")))
A12: Freed each month if you hit target (vs July): | B12: =B5-C5
